<?xml version="1.0" encoding="UTF-8"?>
<metadata xml:lang="zh"><Esri><CreaDate>20200829</CreaDate><CreaTime>11481100</CreaTime><ArcGISFormat>1.0</ArcGISFormat><SyncOnce>TRUE</SyncOnce><DataProperties><itemProps><itemLocation><linkage Sync="TRUE">file://\\POWERGIS\C$\work\code\boundaryMask\shp\boundary</linkage><protocol Sync="TRUE">Local Area Network</protocol></itemLocation></itemProps><copyHistory><copy source="C:\work\code\boundaryMask\boundary" dest="\\POWERGIS\C$\work\code\boundaryMask\shp\boundary" date="20200829" time="11481100"></copy></copyHistory><lineage><Process ToolSource="c:\program files\arcgis\pro\Resources\ArcToolbox\toolboxes\Data Management Tools.tbx\CopyMultiple" Date="20200829" Time="114811">CopyMultiple "C:\work\code\boundaryMask\boundary.shp shapefile_polygon;C:\work\code\boundaryMask\jingshan.shp shapefile_polygon;C:\work\code\boundaryMask\xuhui.shp shapefile_polygon" C:\work\code\boundaryMask\shp boundary;jingshan;xuhui "boundary FeatureClass boundary.shp #;jingshan FeatureClass jingshan.shp #;xuhui FeatureClass xuhui.shp #"</Process></lineage></DataProperties></Esri></metadata>
